{
  "docs": {
    "Guide": [
      "install",
      "get-started",
      "layout",
      "cluster",
      "scales",
      "define",
      "shiny",
      "tips"
    ],
    "Credits": [
      "credits"
    ],
    "News": [
      "news"
    ],
    "Docs": [
      "affiliation_graph",
      "change_dimensions",
      "cran_deps_graph",
      "definitions",
      "extract_graph",
      "generate",
      "graph_background",
      "graph_camera_fov",
      "graph_camera_position",
      "graph_cluster",
      "graph_draw",
      "graph_events",
      "graph_focus_node",
      "graph_layout_bin",
      "graph_layout_live",
      "graph_layout_offline",
      "graph_layout_stable",
      "graph_layout_static",
      "graph_links",
      "graph_nodes",
      "graph_palette",
      "graph-shiny",
      "graph",
      "grapher_demo",
      "link_distance",
      "pin_nodes",
      "pipe",
      "remove_coordinates",
      "remove",
      "rescale_layout",
      "retrieve",
      "save_graph",
      "scale_link_color",
      "scale_node_color",
      "scale_node_size",
      "update_link",
      "update_links",
      "update_node",
      "update_nodes"
    ]
  }
}
